fiddles_demo/__init__.py
fiddles_demo/wild.py
fiddles_demo-0.1.2.dist-info/METADATA
fiddles_demo-0.1.2.dist-info/WHEEL
fiddles_demo-0.1.2.dist-info/RECORD
